[{"id":"6944B2AA0D09FE8A","reports":[{"HRT":["791526222812218"],"Host":["manny"],"ThreadID":["1"],"Agent":["GarbageCollection"],"Edge":["0000000000000000"],"ProcessID":["8017@manny"],"Timestamp":["1384989788371"],"ThreadName":["main"],"version":"X-Trace Report ver 1.0","X-Trace":["196944B2AA0D09FE8A24E44608F9C6A944"],"Tag":["GC"],"Class":["edu.berkeley.xtrace.XTraceContext"],"Label":["Start Trace: Starting GC Tracing"]},
{"Cycles":["20924315"],"Operation":["GC"],"HRT":["791526908438914"],"Host":["manny"],"Option":["CF0400000000"],"ThreadID":["7"],"GcName":["PS Scavenge"],"Edge":["24E44608F9C6A944"],"NumOptions":["1"],"ProcessID":["8017@manny"],"Timestamp":["1384989789057"],"ThreadName":["Service Thread"],"version":"X-Trace Report ver 1.0","GcStart":["1384989789025"],"X-Trace":["196944B2AA0D09FE8AEDA105F6B0ED1BD9"],"Class":["edu.brown.cs.systems.xtrace.resourcetracing.background.GarbageCollection"],"GcCause":["Allocation Failure"],"GcAction":["end of minor GC"],"GcDuration":["10"]},
{"Cycles":["24845053"],"Operation":["GC"],"HRT":["791527449658232"],"Host":["manny"],"Option":["CF0400000000"],"ThreadID":["7"],"GcName":["PS Scavenge"],"Edge":["EDA105F6B0ED1BD9"],"NumOptions":["1"],"ProcessID":["8017@manny"],"Timestamp":["1384989789598"],"ThreadName":["Service Thread"],"version":"X-Trace Report ver 1.0","GcStart":["1384989789582"],"X-Trace":["196944B2AA0D09FE8AE0BD7934FB360D9A"],"Class":["edu.brown.cs.systems.xtrace.resourcetracing.background.GarbageCollection"],"GcCause":["Allocation Failure"],"GcAction":["end of minor GC"],"GcDuration":["11"]},
{"Cycles":["27136946"],"Operation":["GC"],"HRT":["791528126024343"],"Host":["manny"],"Option":["CF0400000000"],"ThreadID":["7"],"GcName":["PS Scavenge"],"Edge":["E0BD7934FB360D9A"],"NumOptions":["1"],"ProcessID":["8017@manny"],"Timestamp":["1384989790274"],"ThreadName":["Service Thread"],"version":"X-Trace Report ver 1.0","GcStart":["1384989790246"],"X-Trace":["196944B2AA0D09FE8A2525B0A501F82399"],"Class":["edu.brown.cs.systems.xtrace.resourcetracing.background.GarbageCollection"],"GcCause":["Allocation Failure"],"GcAction":["end of minor GC"],"GcDuration":["25"]}]},
{"id":"438AE15464ED9BC3","reports":[{"HRT":["791506701502920"],"Host":["manny"],"ThreadID":["1"],"Agent":["GarbageCollection"],"Edge":["0000000000000000"],"ProcessID":["7838@manny"],"Timestamp":["1384989768850"],"ThreadName":["main"],"version":"X-Trace Report ver 1.0","X-Trace":["19438AE15464ED9BC37EF82CE98B84355D"],"Tag":["GC"],"Class":["edu.berkeley.xtrace.XTraceContext"],"Label":["Start Trace: Starting GC Tracing"]},
{"Cycles":["8888859"],"Operation":["GC"],"HRT":["791507356557151"],"Host":["manny"],"Option":["CF0400000000"],"ThreadID":["7"],"GcName":["PS Scavenge"],"Edge":["7EF82CE98B84355D"],"NumOptions":["1"],"ProcessID":["7838@manny"],"Timestamp":["1384989769505"],"ThreadName":["Service Thread"],"version":"X-Trace Report ver 1.0","GcStart":["1384989769478"],"X-Trace":["19438AE15464ED9BC3E78D2BBA72C8B875"],"Class":["edu.brown.cs.systems.xtrace.resourcetracing.background.GarbageCollection"],"GcCause":["Allocation Failure"],"GcAction":["end of minor GC"],"GcDuration":["16"]},
{"Cycles":["13154167"],"Operation":["GC"],"HRT":["791512913588929"],"Host":["manny"],"Option":["CF0400000000"],"ThreadID":["7"],"GcName":["PS Scavenge"],"Edge":["E78D2BBA72C8B875"],"NumOptions":["1"],"ProcessID":["7838@manny"],"Timestamp":["1384989775062"],"ThreadName":["Service Thread"],"version":"X-Trace Report ver 1.0","GcStart":["1384989775039"],"X-Trace":["19438AE15464ED9BC37CFA4410FA06A4A5"],"Class":["edu.brown.cs.systems.xtrace.resourcetracing.background.GarbageCollection"],"GcCause":["Allocation Failure"],"GcAction":["end of minor GC"],"GcDuration":["18"]},
{"Cycles":["16153874"],"Operation":["GC"],"HRT":["791518236414981"],"Host":["manny"],"Option":["CF0400000000"],"ThreadID":["7"],"GcName":["PS Scavenge"],"Edge":["7CFA4410FA06A4A5"],"NumOptions":["1"],"ProcessID":["7838@manny"],"Timestamp":["1384989780385"],"ThreadName":["Service Thread"],"version":"X-Trace Report ver 1.0","GcStart":["1384989780369"],"X-Trace":["19438AE15464ED9BC304639B88BEEADA29"],"Class":["edu.brown.cs.systems.xtrace.resourcetracing.background.GarbageCollection"],"GcCause":["Allocation Failure"],"GcAction":["end of minor GC"],"GcDuration":["12"]},
{"Cycles":["18478835"],"Operation":["GC"],"HRT":["791528182104667"],"Host":["manny"],"Option":["CF0400000000"],"ThreadID":["7"],"GcName":["PS Scavenge"],"Edge":["04639B88BEEADA29"],"NumOptions":["1"],"ProcessID":["7838@manny"],"Timestamp":["1384989790330"],"ThreadName":["Service Thread"],"version":"X-Trace Report ver 1.0","GcStart":["1384989790308"],"X-Trace":["19438AE15464ED9BC3D648C9D1DEFD7634"],"Class":["edu.brown.cs.systems.xtrace.resourcetracing.background.GarbageCollection"],"GcCause":["Allocation Failure"],"GcAction":["end of minor GC"],"GcDuration":["20"]}]},
{"id":"32882402FE34FB72","reports":[{"HRT":["791498561347566"],"Host":["manny"],"ThreadID":["1"],"Agent":["GarbageCollection"],"Edge":["0000000000000000"],"ProcessID":["7725@manny"],"Timestamp":["1384989760710"],"ThreadName":["main"],"version":"X-Trace Report ver 1.0","X-Trace":["1932882402FE34FB725CD0AA4BF4005319"],"Tag":["GC"],"Class":["edu.berkeley.xtrace.XTraceContext"],"Label":["Start Trace: Starting GC Tracing"]},
{"Cycles":["15530896"],"Operation":["GC"],"HRT":["791499141252168"],"Host":["manny"],"Option":["CF0400000000"],"ThreadID":["7"],"GcName":["PS Scavenge"],"Edge":["5CD0AA4BF4005319"],"NumOptions":["1"],"ProcessID":["7725@manny"],"Timestamp":["1384989761290"],"ThreadName":["Service Thread"],"version":"X-Trace Report ver 1.0","GcStart":["1384989761265"],"X-Trace":["1932882402FE34FB720DFC0E7E9F6C5EEE"],"Class":["edu.brown.cs.systems.xtrace.resourcetracing.background.GarbageCollection"],"GcCause":["Allocation Failure"],"GcAction":["end of minor GC"],"GcDuration":["8"]},
{"Cycles":["18675024"],"Operation":["GC"],"HRT":["791504660237642"],"Host":["manny"],"Option":["CF0400000000"],"ThreadID":["7"],"GcName":["PS Scavenge"],"Edge":["0DFC0E7E9F6C5EEE"],"NumOptions":["1"],"ProcessID":["7725@manny"],"Timestamp":["1384989766809"],"ThreadName":["Service Thread"],"version":"X-Trace Report ver 1.0","GcStart":["1384989766786"],"X-Trace":["1932882402FE34FB7218DFCD0CD6164D9F"],"Class":["edu.brown.cs.systems.xtrace.resourcetracing.background.GarbageCollection"],"GcCause":["Allocation Failure"],"GcAction":["end of minor GC"],"GcDuration":["18"]},
{"Cycles":["21121118"],"Operation":["GC"],"HRT":["791509966194823"],"Host":["manny"],"Option":["CF0400000000"],"ThreadID":["7"],"GcName":["PS Scavenge"],"Edge":["18DFCD0CD6164D9F"],"NumOptions":["1"],"ProcessID":["7725@manny"],"Timestamp":["1384989772115"],"ThreadName":["Service Thread"],"version":"X-Trace Report ver 1.0","GcStart":["1384989772098"],"X-Trace":["1932882402FE34FB725DC1CEA68D36C4C1"],"Class":["edu.brown.cs.systems.xtrace.resourcetracing.background.GarbageCollection"],"GcCause":["Allocation Failure"],"GcAction":["end of minor GC"],"GcDuration":["13"]},
{"Cycles":["23452023"],"Operation":["GC"],"HRT":["791528265578201"],"Host":["manny"],"Option":["CF0400000000"],"ThreadID":["7"],"GcName":["PS Scavenge"],"Edge":["5DC1CEA68D36C4C1"],"NumOptions":["1"],"ProcessID":["7725@manny"],"Timestamp":["1384989790414"],"ThreadName":["Service Thread"],"version":"X-Trace Report ver 1.0","GcStart":["1384989790392"],"X-Trace":["1932882402FE34FB72051C995B4497BA7D"],"Class":["edu.brown.cs.systems.xtrace.resourcetracing.background.GarbageCollection"],"GcCause":["Allocation Failure"],"GcAction":["end of minor GC"],"GcDuration":["18"]}]},
{"id":"39DFE62AFC1DA334","reports":[{"HRT":["791529153302261"],"Host":["manny"],"ThreadID":["1"],"Agent":["GarbageCollection"],"Edge":["0000000000000000"],"ProcessID":["8065@manny"],"Timestamp":["1384989791302"],"ThreadName":["main"],"version":"X-Trace Report ver 1.0","X-Trace":["1939DFE62AFC1DA33465E3011DFA48778D"],"Tag":["GC"],"Class":["edu.berkeley.xtrace.XTraceContext"],"Label":["Start Trace: Starting GC Tracing"]},
{"Cycles":["10234951"],"Operation":["GC"],"HRT":["791529825932692"],"Host":["manny"],"Option":["CF0400000000"],"ThreadID":["7"],"GcName":["PS Scavenge"],"Edge":["65E3011DFA48778D"],"NumOptions":["1"],"ProcessID":["8065@manny"],"Timestamp":["1384989791974"],"ThreadName":["Service Thread"],"version":"X-Trace Report ver 1.0","GcStart":["1384989791950"],"X-Trace":["1939DFE62AFC1DA334D53E09327E2AFAC2"],"Class":["edu.brown.cs.systems.xtrace.resourcetracing.background.GarbageCollection"],"GcCause":["Allocation Failure"],"GcAction":["end of minor GC"],"GcDuration":["13"]},
{"Cycles":["13261814"],"Operation":["GC"],"HRT":["791530187405192"],"Host":["manny"],"Option":["CF0400000000"],"ThreadID":["7"],"GcName":["PS Scavenge"],"Edge":["D53E09327E2AFAC2"],"NumOptions":["1"],"ProcessID":["8065@manny"],"Timestamp":["1384989792336"],"ThreadName":["Service Thread"],"version":"X-Trace Report ver 1.0","GcStart":["1384989792323"],"X-Trace":["1939DFE62AFC1DA334B556FEF871B5D09C"],"Class":["edu.brown.cs.systems.xtrace.resourcetracing.background.GarbageCollection"],"GcCause":["Allocation Failure"],"GcAction":["end of minor GC"],"GcDuration":["9"]}]},
{"id":"3DF921E7C042BE9F","reports":[{"HRT":["791533074491886"],"Host":["manny"],"ThreadID":["1"],"Agent":["GarbageCollection"],"Edge":["0000000000000000"],"ProcessID":["8114@manny"],"Timestamp":["1384989795223"],"ThreadName":["main"],"version":"X-Trace Report ver 1.0","X-Trace":["193DF921E7C042BE9F9E1AF7F62C45AA7C"],"Tag":["GC"],"Class":["edu.berkeley.xtrace.XTraceContext"],"Label":["Start Trace: Starting GC Tracing"]},
{"Cycles":["21242734"],"Operation":["GC"],"HRT":["791533760333192"],"Host":["manny"],"Option":["CF0400000000"],"ThreadID":["7"],"GcName":["PS Scavenge"],"Edge":["9E1AF7F62C45AA7C"],"NumOptions":["1"],"ProcessID":["8114@manny"],"Timestamp":["1384989795909"],"ThreadName":["Service Thread"],"version":"X-Trace Report ver 1.0","GcStart":["1384989795878"],"X-Trace":["193DF921E7C042BE9FA289635E0E15FA24"],"Class":["edu.brown.cs.systems.xtrace.resourcetracing.background.GarbageCollection"],"GcCause":["Allocation Failure"],"GcAction":["end of minor GC"],"GcDuration":["8"]},
{"Cycles":["25525498"],"Operation":["GC"],"HRT":["791534301188051"],"Host":["manny"],"Option":["CF0400000000"],"ThreadID":["7"],"GcName":["PS Scavenge"],"Edge":["A289635E0E15FA24"],"NumOptions":["1"],"ProcessID":["8114@manny"],"Timestamp":["1384989796450"],"ThreadName":["Service Thread"],"version":"X-Trace Report ver 1.0","GcStart":["1384989796432"],"X-Trace":["193DF921E7C042BE9FDB833E7AD403BA89"],"Class":["edu.brown.cs.systems.xtrace.resourcetracing.background.GarbageCollection"],"GcCause":["Allocation Failure"],"GcAction":["end of minor GC"],"GcDuration":["10"]},
{"Cycles":["33391747"],"Operation":["GC"],"HRT":["791534616576739"],"Host":["manny"],"Option":["CF0400000000"],"ThreadID":["7"],"GcName":["PS Scavenge"],"Edge":["DB833E7AD403BA89"],"NumOptions":["1"],"ProcessID":["8114@manny"],"Timestamp":["1384989796765"],"ThreadName":["Service Thread"],"version":"X-Trace Report ver 1.0","GcStart":["1384989796744"],"X-Trace":["193DF921E7C042BE9F70FDFE4C83CB1FA3"],"Class":["edu.brown.cs.systems.xtrace.resourcetracing.background.GarbageCollection"],"GcCause":["Allocation Failure"],"GcAction":["end of minor GC"],"GcDuration":["12"]}]},
{"id":"45A28AD184EAF469","reports":[{"HRT":["791535113234574"],"Host":["manny"],"ThreadID":["1"],"Agent":["GarbageCollection"],"Edge":["0000000000000000"],"ProcessID":["8153@manny"],"Timestamp":["1384989797262"],"ThreadName":["main"],"version":"X-Trace Report ver 1.0","X-Trace":["1945A28AD184EAF4699A7A05B8595EBF7D"],"Tag":["GC"],"Class":["edu.berkeley.xtrace.XTraceContext"],"Label":["Start Trace: Starting GC Tracing"]},
{"Cycles":["9094654"],"Operation":["GC"],"HRT":["791535786101582"],"Host":["manny"],"Option":["CF0400000000"],"ThreadID":["7"],"GcName":["PS Scavenge"],"Edge":["9A7A05B8595EBF7D"],"NumOptions":["1"],"ProcessID":["8153@manny"],"Timestamp":["1384989797934"],"ThreadName":["Service Thread"],"version":"X-Trace Report ver 1.0","GcStart":["1384989797916"],"X-Trace":["1945A28AD184EAF469C93C1CF86745D22F"],"Class":["edu.brown.cs.systems.xtrace.resourcetracing.background.GarbageCollection"],"GcCause":["Allocation Failure"],"GcAction":["end of minor GC"],"GcDuration":["9"]},
{"Cycles":["19496508"],"Operation":["GC"],"HRT":["791536323965206"],"Host":["manny"],"Option":["CF0400000000"],"ThreadID":["7"],"GcName":["PS Scavenge"],"Edge":["C93C1CF86745D22F"],"NumOptions":["1"],"ProcessID":["8153@manny"],"Timestamp":["1384989798472"],"ThreadName":["Service Thread"],"version":"X-Trace Report ver 1.0","GcStart":["1384989798450"],"X-Trace":["1945A28AD184EAF46937CB9FB18D04FB63"],"Class":["edu.brown.cs.systems.xtrace.resourcetracing.background.GarbageCollection"],"GcCause":["Allocation Failure"],"GcAction":["end of minor GC"],"GcDuration":["11"]},
{"Cycles":["22068246"],"Operation":["GC"],"HRT":["791536641293460"],"Host":["manny"],"Option":["CF0400000000"],"ThreadID":["7"],"GcName":["PS Scavenge"],"Edge":["37CB9FB18D04FB63"],"NumOptions":["1"],"ProcessID":["8153@manny"],"Timestamp":["1384989798790"],"ThreadName":["Service Thread"],"version":"X-Trace Report ver 1.0","GcStart":["1384989798777"],"X-Trace":["1945A28AD184EAF469E408FA1B6D369D54"],"Class":["edu.brown.cs.systems.xtrace.resourcetracing.background.GarbageCollection"],"GcCause":["Allocation Failure"],"GcAction":["end of minor GC"],"GcDuration":["10"]},
{"Cycles":["24397641"],"Operation":["GC"],"HRT":["791537086444211"],"Host":["manny"],"Option":["CF0400000000"],"ThreadID":["7"],"GcName":["PS Scavenge"],"Edge":["E408FA1B6D369D54"],"NumOptions":["1"],"ProcessID":["8153@manny"],"Timestamp":["1384989799235"],"ThreadName":["Service Thread"],"version":"X-Trace Report ver 1.0","GcStart":["1384989799204"],"X-Trace":["1945A28AD184EAF4698540DF14F55FC9F3"],"Class":["edu.brown.cs.systems.xtrace.resourcetracing.background.GarbageCollection"],"GcCause":["Allocation Failure"],"GcAction":["end of minor GC"],"GcDuration":["26"]}]},
{"id":"82F23A1D8A02E75C","reports":[{"HRT":["791537898552816"],"Host":["manny"],"ThreadID":["1"],"Agent":["GarbageCollection"],"Edge":["0000000000000000"],"ProcessID":["8201@manny"],"Timestamp":["1384989800047"],"ThreadName":["main"],"version":"X-Trace Report ver 1.0","X-Trace":["1982F23A1D8A02E75C58AC4E6FEBDCB1CB"],"Tag":["GC"],"Class":["edu.berkeley.xtrace.XTraceContext"],"Label":["Start Trace: Starting GC Tracing"]},
{"Cycles":["17688249"],"Operation":["GC"],"HRT":["791538573536656"],"Host":["manny"],"Option":["CF0400000000"],"ThreadID":["7"],"GcName":["PS Scavenge"],"Edge":["58AC4E6FEBDCB1CB"],"NumOptions":["1"],"ProcessID":["8201@manny"],"Timestamp":["1384989800722"],"ThreadName":["Service Thread"],"version":"X-Trace Report ver 1.0","GcStart":["1384989800696"],"X-Trace":["1982F23A1D8A02E75C68486A6C7B311481"],"Class":["edu.brown.cs.systems.xtrace.resourcetracing.background.GarbageCollection"],"GcCause":["Allocation Failure"],"GcAction":["end of minor GC"],"GcDuration":["8"]},
{"Cycles":["21082036"],"Operation":["GC"],"HRT":["791539097739567"],"Host":["manny"],"Option":["CF0400000000"],"ThreadID":["7"],"GcName":["PS Scavenge"],"Edge":["68486A6C7B311481"],"NumOptions":["1"],"ProcessID":["8201@manny"],"Timestamp":["1384989801246"],"ThreadName":["Service Thread"],"version":"X-Trace Report ver 1.0","GcStart":["1384989801233"],"X-Trace":["1982F23A1D8A02E75C487D899461D95229"],"Class":["edu.brown.cs.systems.xtrace.resourcetracing.background.GarbageCollection"],"GcCause":["Allocation Failure"],"GcAction":["end of minor GC"],"GcDuration":["10"]},
{"Cycles":["23399655"],"Operation":["GC"],"HRT":["791539402216646"],"Host":["manny"],"Option":["CF0400000000"],"ThreadID":["7"],"GcName":["PS Scavenge"],"Edge":["487D899461D95229"],"NumOptions":["1"],"ProcessID":["8201@manny"],"Timestamp":["1384989801551"],"ThreadName":["Service Thread"],"version":"X-Trace Report ver 1.0","GcStart":["1384989801537"],"X-Trace":["1982F23A1D8A02E75C8C022823F02BEF76"],"Class":["edu.brown.cs.systems.xtrace.resourcetracing.background.GarbageCollection"],"GcCause":["Allocation Failure"],"GcAction":["end of minor GC"],"GcDuration":["11"]}]},
{"id":"F8E31A2BF406EE16","reports":[{"HRT":["791577853342133"],"Host":["manny"],"ThreadID":["1"],"Agent":["GarbageCollection"],"Edge":["0000000000000000"],"ProcessID":["8282@manny"],"Timestamp":["1384989840002"],"ThreadName":["main"],"version":"X-Trace Report ver 1.0","X-Trace":["19F8E31A2BF406EE16CA34F59AF5FC3AD7"],"Tag":["GC"],"Class":["edu.berkeley.xtrace.XTraceContext"],"Label":["Start Trace: Starting GC Tracing"]}]}]
